MANIFEST.in
README.md
pyproject.toml
setup.py
mercury/__init__.py
mercury/demo.py
mercury/manage.py
mercury/mercury.py
mercury/requirements.txt
mercury/start_instance.py
mercury/apps/__init__.py
mercury/apps/accounts/__init__.py
mercury/apps/accounts/admin.py
mercury/apps/accounts/apps.py
mercury/apps/accounts/fields.py
mercury/apps/accounts/models.py
mercury/apps/accounts/serializers.py
mercury/apps/accounts/tasks.py
mercury/apps/accounts/urls.py
mercury/apps/accounts/migrations/0001_initial.py
mercury/apps/accounts/migrations/__init__.py
mercury/apps/accounts/tests/__init__.py
mercury/apps/accounts/tests/test_accounts.py
mercury/apps/accounts/tests/test_invitations.py
mercury/apps/accounts/tests/test_secrets.py
mercury/apps/accounts/tests/test_sites.py
mercury/apps/accounts/tests/test_subscription.py
mercury/apps/accounts/views/__init__.py
mercury/apps/accounts/views/accounts.py
mercury/apps/accounts/views/invitations.py
mercury/apps/accounts/views/permissions.py
mercury/apps/accounts/views/secrets.py
mercury/apps/accounts/views/sites.py
mercury/apps/accounts/views/subscription.py
mercury/apps/accounts/views/utils.py
mercury/apps/nb/__init__.py
mercury/apps/nb/exporter.py
mercury/apps/nb/nbrun.py
mercury/apps/nb/tests.py
mercury/apps/nb/utils.py
mercury/apps/nb/tests/__init__.py
mercury/apps/nb/tests/test_nbrun.py
mercury/apps/nbworker/__init__.py
mercury/apps/nbworker/__main__.py
mercury/apps/nbworker/nb.py
mercury/apps/nbworker/rest.py
mercury/apps/nbworker/tests.py
mercury/apps/nbworker/utils.py
mercury/apps/nbworker/ws.py
mercury/apps/notebooks/__init__.py
mercury/apps/notebooks/admin.py
mercury/apps/notebooks/apps.py
mercury/apps/notebooks/models.py
mercury/apps/notebooks/serializers.py
mercury/apps/notebooks/slides_themes.py
mercury/apps/notebooks/tasks.py
mercury/apps/notebooks/tests.py
mercury/apps/notebooks/urls.py
mercury/apps/notebooks/views.py
mercury/apps/notebooks/management/__init__.py
mercury/apps/notebooks/management/commands/__init__.py
mercury_dev.egg-info/PKG-INFO
mercury_dev.egg-info/SOURCES.txt
mercury_dev.egg-info/dependency_links.txt
mercury_dev.egg-info/entry_points.txt
mercury_dev.egg-info/requires.txt
mercury_dev.egg-info/top_level.txt