Metadata-Version: 2.1
Name: mercury-dev
Version: 2.3.10
Summary: Turn Jupyter Notebook to Web App and share with non-technical users
Home-page: https://github.com/mljar/mercury
Author: MLJAR Sp. z o.o.
Maintainer: MLJAR Sp. z o.o.
Maintainer-email: contact@mljar.com
License: UNKNOWN
Platform: UNKNOWN
Classifier: Operating System :: OS Independent
Classifier: Programming Language :: Python
Classifier: Programming Language :: Python :: 3.8
Classifier: Programming Language :: Python :: 3.9
Classifier: Programming Language :: Python :: 3.10
Classifier: Programming Language :: Python :: 3.11
Requires-Python: >=3.8
